{
  "uri": "/api/ip-acl",
  "comments": [
    "Creates an IP Access Control List. You can optionally specify an Id on this create request, if one is not provided one will be generated."
  ],
  "method": "post",
  "methodName": "createIPAccessControlList",
  "successResponse": "IPAccessControlListResponse",
  "errorResponse": "Errors",
  "params": [
    {
      "name": "accessControlListId",
      "comments": [
        "(Optional) The Id for the IP Access Control List. If not provided a secure random UUID will be generated."
      ],
      "type": "urlSegment",
      "javaType": "UUID"
    },
    {
      "name": "request",
      "comments": [
        "The request object that contains all of the information used to create the IP Access Control List."
      ],
      "type": "body",
      "javaType": "IPAccessControlListRequest"
    }
  ]
}