{
  "className" : "io.fusionauth.domain.api.GroupRequest",
  "extends" : {
    "className" : "java.lang.Object",
    "type" : "Object",
    "typeArguments" : [ ]
  },
  "fields" : {
    "group" : {
      "className" : "io.fusionauth.domain.Group",
      "type" : "Group"
    },
    "roleIds" : {
      "className" : "java.util.List",
      "type" : "List",
      "typeArguments" : [ {
        "className" : "java.util.UUID",
        "type" : "UUID"
      } ]
    }
  },
  "interfaces" : [ {
    "className" : "io.fusionauth.domain.Buildable",
    "type" : "Buildable",
    "typeArguments" : [ {
      "className" : "io.fusionauth.domain.api.GroupRequest",
      "type" : "GroupRequest"
    } ]
  } ],
  "objectType" : "Object",
  "packageName" : "io.fusionauth.domain.api",
  "type" : "GroupRequest"
}